racoon/__init__.py
racoon/argument_types.py
racoon/git.py
racoon/github_integration.py
racoon/main.py
racoon/repo.py
racoon/template_generation.py
racoon/version.py
py_racoon-0.1.5.dist-info/LICENSE
py_racoon-0.1.5.dist-info/METADATA
py_racoon-0.1.5.dist-info/WHEEL
py_racoon-0.1.5.dist-info/entry_points.txt
py_racoon-0.1.5.dist-info/top_level.txt
py_racoon-0.1.5.dist-info/RECORD
